pyone/__init__.py
pyone/acl.py
pyone/helpers.py
pyone/server.py
pyone/tester.py
pyone/util.py
pyone/bindings/__init__.py
pyone/bindings/supbind.py
pyone-7.0.2.dist-info/LICENSE
pyone-7.0.2.dist-info/METADATA
pyone-7.0.2.dist-info/WHEEL
pyone-7.0.2.dist-info/top_level.txt
pyone-7.0.2.dist-info/RECORD
