Metadata-Version: 2.1
Name: pyone
Version: 7.0.2
Summary: Python Bindings for OpenNebula XML-RPC API
Home-page: http://opennebula.io
Author: Rafael del Valle
Author-email: rvalle@privaz.io
License: http://www.apache.org/licenses/LICENSE-2.0
Keywords: cloud opennebula xmlrpc bindings
Platform: UNKNOWN
Classifier: Development Status :: 4 - Beta
Classifier: Intended Audience :: Developers
Classifier: Topic :: Software Development :: Build Tools
Classifier: License :: OSI Approved :: Apache Software License
Classifier: Programming Language :: Python :: 3
License-File: LICENSE
Requires-Dist: dict2xml
Requires-Dist: lxml
Requires-Dist: requests
Requires-Dist: six
Requires-Dist: tblib
Requires-Dist: xmltodict
Provides-Extra: dev
Requires-Dist: check-manifest ; extra == 'dev'
Provides-Extra: test
Requires-Dist: coverage ; extra == 'test'
